{
    "data": [
        {
            "from": "2023-12-09T17:30Z",
            "to": "2023-12-09T18:00Z",
            "intensity": {
                "forecast": 104,
                "actual": null,
                "index": "low"
            }
        },
        {
            "from": "2023-12-09T18:00Z",
            "to": "2023-12-09T18:30Z",
            "intensity": {
                "forecast": 104,
                "actual": null,
                "index": "low"
            }
        },
        {
            "from": "2023-12-09T18:30Z",
            "to": "2023-12-09T19:00Z",
            "intensity": {
                "forecast": 100,
                "actual": null,
                "index": "low"
            }
        },
        {
            "from": "2023-12-09T19:00Z",
            "to": "2023-12-09T19:30Z",
            "intensity": {
                "forecast": 91,
                "actual": null,
                "index": "low"
            }
        },
        {
            "from": "2023-12-09T19:30Z",
            "to": "2023-12-09T20:00Z",
            "intensity": {
                "forecast": 84,
                "actual": null,
                "index": "low"
            }
        },
        {
            "from": "2023-12-09T20:00Z",
            "to": "2023-12-09T20:30Z",
            "intensity": {
                "forecast": 82,
                "actual": null,
                "index": "low"
            }
        },
        {
            "from": "2023-12-09T20:30Z",
            "to": "2023-12-09T21:00Z",
            "intensity": {
                "forecast": 82,
                "actual": null,
                "index": "low"
            }
        },
        {
            "from": "2023-12-09T21:00Z",
            "to": "2023-12-09T21:30Z",
            "intensity": {
                "forecast": 79,
                "actual": null,
                "index": "low"
            }
        },
        {
            "from": "2023-12-09T21:30Z",
            "to": "2023-12-09T22:00Z",
            "intensity": {
                "forecast": 75,
                "actual": null,
                "index": "low"
            }
        },
        {
            "from": "2023-12-09T22:00Z",
            "to": "2023-12-09T22:30Z",
            "intensity": {
                "forecast": 69,
                "actual": null,
                "index": "low"
            }
        },
        {
            "from": "2023-12-09T22:30Z",
            "to": "2023-12-09T23:00Z",
            "intensity": {
                "forecast": 67,
                "actual": null,
                "index": "low"
            }
        },
        {
            "from": "2023-12-09T23:00Z",
            "to": "2023-12-09T23:30Z",
            "intensity": {
                "forecast": 69,
                "actual": null,
                "index": "low"
            }
        },
        {
            "from": "2023-12-09T23:30Z",
            "to": "2023-12-10T00:00Z",
            "intensity": {
                "forecast": 71,
                "actual": null,
                "index": "low"
            }
        },
        {
            "from": "2023-12-10T00:00Z",
            "to": "2023-12-10T00:30Z",
            "intensity": {
                "forecast": 75,
                "actual": null,
                "index": "low"
            }
        },
        {
            "from": "2023-12-10T00:30Z",
            "to": "2023-12-10T01:00Z",
            "intensity": {
                "forecast": 77,
                "actual": null,
                "index": "low"
            }
        },
        {
            "from": "2023-12-10T01:00Z",
            "to": "2023-12-10T01:30Z",
            "intensity": {
                "forecast": 78,
                "actual": null,
                "index": "low"
            }
        },
        {
            "from": "2023-12-10T01:30Z",
            "to": "2023-12-10T02:00Z",
            "intensity": {
                "forecast": 83,
                "actual": null,
                "index": "low"
            }
        },
        {
            "from": "2023-12-10T02:00Z",
            "to": "2023-12-10T02:30Z",
            "intensity": {
                "forecast": 84,
                "actual": null,
                "index": "low"
            }
        },
        {
            "from": "2023-12-10T02:30Z",
            "to": "2023-12-10T03:00Z",
            "intensity": {
                "forecast": 86,
                "actual": null,
                "index": "low"
            }
        },
        {
            "from": "2023-12-10T03:00Z",
            "to": "2023-12-10T03:30Z",
            "intensity": {
                "forecast": 85,
                "actual": null,
                "index": "low"
            }
        },
        {
            "from": "2023-12-10T03:30Z",
            "to": "2023-12-10T04:00Z",
            "intensity": {
                "forecast": 86,
                "actual": null,
                "index": "low"
            }
        },
        {
            "from": "2023-12-10T04:00Z",
            "to": "2023-12-10T04:30Z",
            "intensity": {
                "forecast": 88,
                "actual": null,
                "index": "low"
            }
        },
        {
            "from": "2023-12-10T04:30Z",
            "to": "2023-12-10T05:00Z",
            "intensity": {
                "forecast": 85,
                "actual": null,
                "index": "low"
            }
        },
        {
            "from": "2023-12-10T05:00Z",
            "to": "2023-12-10T05:30Z",
            "intensity": {
                "forecast": 88,
                "actual": null,
                "index": "low"
            }
        },
        {
            "from": "2023-12-10T05:30Z",
            "to": "2023-12-10T06:00Z",
            "intensity": {
                "forecast": 94,
                "actual": null,
                "index": "low"
            }
        },
        {
            "from": "2023-12-10T06:00Z",
            "to": "2023-12-10T06:30Z",
            "intensity": {
                "forecast": 100,
                "actual": null,
                "index": "low"
            }
        },
        {
            "from": "2023-12-10T06:30Z",
            "to": "2023-12-10T07:00Z",
            "intensity": {
                "forecast": 105,
                "actual": null,
                "index": "low"
            }
        },
        {
            "from": "2023-12-10T07:00Z",
            "to": "2023-12-10T07:30Z",
            "intensity": {
                "forecast": 107,
                "actual": null,
                "index": "low"
            }
        },
        {
            "from": "2023-12-10T07:30Z",
            "to": "2023-12-10T08:00Z",
            "intensity": {
                "forecast": 113,
                "actual": null,
                "index": "low"
            }
        },
        {
            "from": "2023-12-10T08:00Z",
            "to": "2023-12-10T08:30Z",
            "intensity": {
                "forecast": 122,
                "actual": null,
                "index": "moderate"
            }
        },
        {
            "from": "2023-12-10T08:30Z",
            "to": "2023-12-10T09:00Z",
            "intensity": {
                "forecast": 138,
                "actual": null,
                "index": "moderate"
            }
        },
        {
            "from": "2023-12-10T09:00Z",
            "to": "2023-12-10T09:30Z",
            "intensity": {
                "forecast": 145,
                "actual": null,
                "index": "moderate"
            }
        },
        {
            "from": "2023-12-10T09:30Z",
            "to": "2023-12-10T10:00Z",
            "intensity": {
                "forecast": 146,
                "actual": null,
                "index": "moderate"
            }
        },
        {
            "from": "2023-12-10T10:00Z",
            "to": "2023-12-10T10:30Z",
            "intensity": {
                "forecast": 150,
                "actual": null,
                "index": "moderate"
            }
        },
        {
            "from": "2023-12-10T10:30Z",
            "to": "2023-12-10T11:00Z",
            "intensity": {
                "forecast": 147,
                "actual": null,
                "index": "moderate"
            }
        },
        {
            "from": "2023-12-10T11:00Z",
            "to": "2023-12-10T11:30Z",
            "intensity": {
                "forecast": 143,
                "actual": null,
                "index": "moderate"
            }
        },
        {
            "from": "2023-12-10T11:30Z",
            "to": "2023-12-10T12:00Z",
            "intensity": {
                "forecast": 148,
                "actual": null,
                "index": "moderate"
            }
        },
        {
            "from": "2023-12-10T12:00Z",
            "to": "2023-12-10T12:30Z",
            "intensity": {
                "forecast": 153,
                "actual": null,
                "index": "moderate"
            }
        },
        {
            "from": "2023-12-10T12:30Z",
            "to": "2023-12-10T13:00Z",
            "intensity": {
                "forecast": 149,
                "actual": null,
                "index": "moderate"
            }
        },
        {
            "from": "2023-12-10T13:00Z",
            "to": "2023-12-10T13:30Z",
            "intensity": {
                "forecast": 148,
                "actual": null,
                "index": "moderate"
            }
        },
        {
            "from": "2023-12-10T13:30Z",
            "to": "2023-12-10T14:00Z",
            "intensity": {
                "forecast": 148,
                "actual": null,
                "index": "moderate"
            }
        },
        {
            "from": "2023-12-10T14:00Z",
            "to": "2023-12-10T14:30Z",
            "intensity": {
                "forecast": 148,
                "actual": null,
                "index": "moderate"
            }
        },
        {
            "from": "2023-12-10T14:30Z",
            "to": "2023-12-10T15:00Z",
            "intensity": {
                "forecast": 150,
                "actual": null,
                "index": "moderate"
            }
        },
        {
            "from": "2023-12-10T15:00Z",
            "to": "2023-12-10T15:30Z",
            "intensity": {
                "forecast": 152,
                "actual": null,
                "index": "moderate"
            }
        },
        {
            "from": "2023-12-10T15:30Z",
            "to": "2023-12-10T16:00Z",
            "intensity": {
                "forecast": 160,
                "actual": null,
                "index": "moderate"
            }
        },
        {
            "from": "2023-12-10T16:00Z",
            "to": "2023-12-10T16:30Z",
            "intensity": {
                "forecast": 163,
                "actual": null,
                "index": "moderate"
            }
        },
        {
            "from": "2023-12-10T16:30Z",
            "to": "2023-12-10T17:00Z",
            "intensity": {
                "forecast": 165,
                "actual": null,
                "index": "moderate"
            }
        },
        {
            "from": "2023-12-10T17:00Z",
            "to": "2023-12-10T17:30Z",
            "intensity": {
                "forecast": 165,
                "actual": null,
                "index": "moderate"
            }
        },
        {
            "from": "2023-12-10T17:30Z",
            "to": "2023-12-10T18:00Z",
            "intensity": {
                "forecast": 157,
                "actual": null,
                "index": "moderate"
            }
        },
        {
            "from": "2023-12-10T18:00Z",
            "to": "2023-12-10T18:30Z",
            "intensity": {
                "forecast": 155,
                "actual": null,
                "index": "moderate"
            }
        },
        {
            "from": "2023-12-10T18:30Z",
            "to": "2023-12-10T19:00Z",
            "intensity": {
                "forecast": 152,
                "actual": null,
                "index": "moderate"
            }
        },
        {
            "from": "2023-12-10T19:00Z",
            "to": "2023-12-10T19:30Z",
            "intensity": {
                "forecast": 149,
                "actual": null,
                "index": "moderate"
            }
        },
        {
            "from": "2023-12-10T19:30Z",
            "to": "2023-12-10T20:00Z",
            "intensity": {
                "forecast": 148,
                "actual": null,
                "index": "moderate"
            }
        },
        {
            "from": "2023-12-10T20:00Z",
            "to": "2023-12-10T20:30Z",
            "intensity": {
                "forecast": 138,
                "actual": null,
                "index": "moderate"
            }
        },
        {
            "from": "2023-12-10T20:30Z",
            "to": "2023-12-10T21:00Z",
            "intensity": {
                "forecast": 124,
                "actual": null,
                "index": "moderate"
            }
        },
        {
            "from": "2023-12-10T21:00Z",
            "to": "2023-12-10T21:30Z",
            "intensity": {
                "forecast": 112,
                "actual": null,
                "index": "low"
            }
        },
        {
            "from": "2023-12-10T21:30Z",
            "to": "2023-12-10T22:00Z",
            "intensity": {
                "forecast": 104,
                "actual": null,
                "index": "low"
            }
        },
        {
            "from": "2023-12-10T22:00Z",
            "to": "2023-12-10T22:30Z",
            "intensity": {
                "forecast": 102,
                "actual": null,
                "index": "low"
            }
        },
        {
            "from": "2023-12-10T22:30Z",
            "to": "2023-12-10T23:00Z",
            "intensity": {
                "forecast": 99,
                "actual": null,
                "index": "low"
            }
        },
        {
            "from": "2023-12-10T23:00Z",
            "to": "2023-12-10T23:30Z",
            "intensity": {
                "forecast": 93,
                "actual": null,
                "index": "low"
            }
        },
        {
            "from": "2023-12-10T23:30Z",
            "to": "2023-12-11T00:00Z",
            "intensity": {
                "forecast": 90,
                "actual": null,
                "index": "low"
            }
        },
        {
            "from": "2023-12-11T00:00Z",
            "to": "2023-12-11T00:30Z",
            "intensity": {
                "forecast": 93,
                "actual": null,
                "index": "low"
            }
        },
        {
            "from": "2023-12-11T00:30Z",
            "to": "2023-12-11T01:00Z",
            "intensity": {
                "forecast": 92,
                "actual": null,
                "index": "low"
            }
        },
        {
            "from": "2023-12-11T01:00Z",
            "to": "2023-12-11T01:30Z",
            "intensity": {
                "forecast": 95,
                "actual": null,
                "index": "low"
            }
        },
        {
            "from": "2023-12-11T01:30Z",
            "to": "2023-12-11T02:00Z",
            "intensity": {
                "forecast": 96,
                "actual": null,
                "index": "low"
            }
        },
        {
            "from": "2023-12-11T02:00Z",
            "to": "2023-12-11T02:30Z",
            "intensity": {
                "forecast": 96,
                "actual": null,
                "index": "low"
            }
        },
        {
            "from": "2023-12-11T02:30Z",
            "to": "2023-12-11T03:00Z",
            "intensity": {
                "forecast": 99,
                "actual": null,
                "index": "low"
            }
        },
        {
            "from": "2023-12-11T03:00Z",
            "to": "2023-12-11T03:30Z",
            "intensity": {
                "forecast": 99,
                "actual": null,
                "index": "low"
            }
        },
        {
            "from": "2023-12-11T03:30Z",
            "to": "2023-12-11T04:00Z",
            "intensity": {
                "forecast": 99,
                "actual": null,
                "index": "low"
            }
        },
        {
            "from": "2023-12-11T04:00Z",
            "to": "2023-12-11T04:30Z",
            "intensity": {
                "forecast": 100,
                "actual": null,
                "index": "low"
            }
        },
        {
            "from": "2023-12-11T04:30Z",
            "to": "2023-12-11T05:00Z",
            "intensity": {
                "forecast": 101,
                "actual": null,
                "index": "low"
            }
        },
        {
            "from": "2023-12-11T05:00Z",
            "to": "2023-12-11T05:30Z",
            "intensity": {
                "forecast": 107,
                "actual": null,
                "index": "low"
            }
        },
        {
            "from": "2023-12-11T05:30Z",
            "to": "2023-12-11T06:00Z",
            "intensity": {
                "forecast": 117,
                "actual": null,
                "index": "low"
            }
        },
        {
            "from": "2023-12-11T06:00Z",
            "to": "2023-12-11T06:30Z",
            "intensity": {
                "forecast": 136,
                "actual": null,
                "index": "moderate"
            }
        },
        {
            "from": "2023-12-11T06:30Z",
            "to": "2023-12-11T07:00Z",
            "intensity": {
                "forecast": 169,
                "actual": null,
                "index": "moderate"
            }
        },
        {
            "from": "2023-12-11T07:00Z",
            "to": "2023-12-11T07:30Z",
            "intensity": {
                "forecast": 191,
                "actual": null,
                "index": "moderate"
            }
        },
        {
            "from": "2023-12-11T07:30Z",
            "to": "2023-12-11T08:00Z",
            "intensity": {
                "forecast": 204,
                "actual": null,
                "index": "high"
            }
        },
        {
            "from": "2023-12-11T08:00Z",
            "to": "2023-12-11T08:30Z",
            "intensity": {
                "forecast": 207,
                "actual": null,
                "index": "high"
            }
        },
        {
            "from": "2023-12-11T08:30Z",
            "to": "2023-12-11T09:00Z",
            "intensity": {
                "forecast": 210,
                "actual": null,
                "index": "high"
            }
        },
        {
            "from": "2023-12-11T09:00Z",
            "to": "2023-12-11T09:30Z",
            "intensity": {
                "forecast": 209,
                "actual": null,
                "index": "high"
            }
        },
        {
            "from": "2023-12-11T09:30Z",
            "to": "2023-12-11T10:00Z",
            "intensity": {
                "forecast": 213,
                "actual": null,
                "index": "high"
            }
        },
        {
            "from": "2023-12-11T10:00Z",
            "to": "2023-12-11T10:30Z",
            "intensity": {
                "forecast": 215,
                "actual": null,
                "index": "high"
            }
        },
        {
            "from": "2023-12-11T10:30Z",
            "to": "2023-12-11T11:00Z",
            "intensity": {
                "forecast": 218,
                "actual": null,
                "index": "high"
            }
        },
        {
            "from": "2023-12-11T11:00Z",
            "to": "2023-12-11T11:30Z",
            "intensity": {
                "forecast": 220,
                "actual": null,
                "index": "high"
            }
        },
        {
            "from": "2023-12-11T11:30Z",
            "to": "2023-12-11T12:00Z",
            "intensity": {
                "forecast": 225,
                "actual": null,
                "index": "high"
            }
        },
        {
            "from": "2023-12-11T12:00Z",
            "to": "2023-12-11T12:30Z",
            "intensity": {
                "forecast": 230,
                "actual": null,
                "index": "high"
            }
        },
        {
            "from": "2023-12-11T12:30Z",
            "to": "2023-12-11T13:00Z",
            "intensity": {
                "forecast": 236,
                "actual": null,
                "index": "high"
            }
        },
        {
            "from": "2023-12-11T13:00Z",
            "to": "2023-12-11T13:30Z",
            "intensity": {
                "forecast": 243,
                "actual": null,
                "index": "high"
            }
        },
        {
            "from": "2023-12-11T13:30Z",
            "to": "2023-12-11T14:00Z",
            "intensity": {
                "forecast": 251,
                "actual": null,
                "index": "high"
            }
        },
        {
            "from": "2023-12-11T14:00Z",
            "to": "2023-12-11T14:30Z",
            "intensity": {
                "forecast": 259,
                "actual": null,
                "index": "high"
            }
        },
        {
            "from": "2023-12-11T14:30Z",
            "to": "2023-12-11T15:00Z",
            "intensity": {
                "forecast": 265,
                "actual": null,
                "index": "high"
            }
        },
        {
            "from": "2023-12-11T15:00Z",
            "to": "2023-12-11T15:30Z",
            "intensity": {
                "forecast": 267,
                "actual": null,
                "index": "high"
            }
        },
        {
            "from": "2023-12-11T15:30Z",
            "to": "2023-12-11T16:00Z",
            "intensity": {
                "forecast": 271,
                "actual": null,
                "index": "high"
            }
        },
        {
            "from": "2023-12-11T16:00Z",
            "to": "2023-12-11T16:30Z",
            "intensity": {
                "forecast": 273,
                "actual": null,
                "index": "high"
            }
        },
        {
            "from": "2023-12-11T16:30Z",
            "to": "2023-12-11T17:00Z",
            "intensity": {
                "forecast": 274,
                "actual": null,
                "index": "high"
            }
        },
        {
            "from": "2023-12-11T17:00Z",
            "to": "2023-12-11T17:30Z",
            "intensity": {
                "forecast": 274,
                "actual": null,
                "index": "high"
            }
        }
    ]
}